{
  "name": "TypeProduit",
  "fields": [
    {
      "fieldName": "id",
      "fieldType": "Long",
      "fieldValidateRules": ["unique", "required"]
    },
    {
      "fieldName": "libelle",
      "fieldType": "String",
      "fieldValidateRules": ["required"]
    },
    {
      "fieldName": "description",
      "fieldType": "String"
    }
  ],
  "relationships": [
    {
      "relationshipType": "one-to-many",
      "otherEntityName": "produit",
      "otherEntityRelationshipName": "typeProduit",
      "relationshipName": "produit"
    }
  ],
  "entityTableName": "type_produit",
  "dto": "no",
  "pagination": "no",
  "service": "no",
  "jpaMetamodelFiltering": false,
  "fluentMethods": true,
  "readOnly": false,
  "embedded": false,
  "applications": ["Jade"],
  "changelogDate": "20211025163458"
}
